my_turing_calculator/__init__.py
my_turing_calculator/hello.py
martin_turing_test_1-0.0.1.dist-info/METADATA
martin_turing_test_1-0.0.1.dist-info/WHEEL
martin_turing_test_1-0.0.1.dist-info/top_level.txt
martin_turing_test_1-0.0.1.dist-info/RECORD
